setup.cfg
setup.py
boxup_bicolormatrix/__init__.py
boxup_bicolormatrix/boxup_bicolormatrix.py
boxup_bicolormatrix.egg-info/PKG-INFO
boxup_bicolormatrix.egg-info/SOURCES.txt
boxup_bicolormatrix.egg-info/dependency_links.txt
boxup_bicolormatrix.egg-info/requires.txt
boxup_bicolormatrix.egg-info/top_level.txt