Metadata-Version: 1.1
Name: boxup-bicolormatrix
Version: 0.0.2
Summary: a visualization implementation for boxup. uses a adafruit bicolor matrix 8x8
Home-page: https://github.com/xamgreen/boxup_bicolormatrix
Author: Maximilian, Noppel
Author-email: noppelmax@googlemail.com
License: GPLv2, see LICENSE.txt
Download-URL: https://github.com/xamgreen/boxup_bicolormatrix/tarball0.0.2
Keywords: weatherradar openweathermap raspberrypi gpio i2c adafruit bicolormatrix
Platform: UNKNOWN
